google-stubs/METADATA.toml
google-stubs/protobuf/__init__.pyi
google-stubs/protobuf/any_pb2.pyi
google-stubs/protobuf/api_pb2.pyi
google-stubs/protobuf/descriptor.pyi
google-stubs/protobuf/descriptor_pb2.pyi
google-stubs/protobuf/descriptor_pool.pyi
google-stubs/protobuf/duration_pb2.pyi
google-stubs/protobuf/empty_pb2.pyi
google-stubs/protobuf/field_mask_pb2.pyi
google-stubs/protobuf/json_format.pyi
google-stubs/protobuf/message.pyi
google-stubs/protobuf/message_factory.pyi
google-stubs/protobuf/py.typed
google-stubs/protobuf/reflection.pyi
google-stubs/protobuf/runtime_version.pyi
google-stubs/protobuf/source_context_pb2.pyi
google-stubs/protobuf/struct_pb2.pyi
google-stubs/protobuf/symbol_database.pyi
google-stubs/protobuf/text_format.pyi
google-stubs/protobuf/timestamp_pb2.pyi
google-stubs/protobuf/type_pb2.pyi
google-stubs/protobuf/wrappers_pb2.pyi
google-stubs/protobuf/compiler/__init__.pyi
google-stubs/protobuf/compiler/plugin_pb2.pyi
google-stubs/protobuf/internal/__init__.pyi
google-stubs/protobuf/internal/api_implementation.pyi
google-stubs/protobuf/internal/builder.pyi
google-stubs/protobuf/internal/containers.pyi
google-stubs/protobuf/internal/decoder.pyi
google-stubs/protobuf/internal/encoder.pyi
google-stubs/protobuf/internal/enum_type_wrapper.pyi
google-stubs/protobuf/internal/extension_dict.pyi
google-stubs/protobuf/internal/message_listener.pyi
google-stubs/protobuf/internal/python_message.pyi
google-stubs/protobuf/internal/type_checkers.pyi
google-stubs/protobuf/internal/well_known_types.pyi
google-stubs/protobuf/internal/wire_format.pyi
google-stubs/protobuf/util/__init__.pyi
types_protobuf-6.30.2.20250503.dist-info/licenses/LICENSE
types_protobuf-6.30.2.20250503.dist-info/METADATA
types_protobuf-6.30.2.20250503.dist-info/WHEEL
types_protobuf-6.30.2.20250503.dist-info/top_level.txt
types_protobuf-6.30.2.20250503.dist-info/RECORD
